finazops/__init__.py
finazops/__main__.py
finazops/cli.py
finazops/natural.py
finazops-0.2.0.dist-info/METADATA
finazops-0.2.0.dist-info/WHEEL
finazops-0.2.0.dist-info/entry_points.txt
finazops-0.2.0.dist-info/top_level.txt
finazops-0.2.0.dist-info/RECORD
