Metadata-Version: 2.4
Name: finazops
Version: 0.2.0
Summary: FinOps CLI Toolkit for Azure
Author-email: Franck Kengne <2monthscloud@gmail.com>
License: MIT
Requires-Python: >=3.8
Requires-Dist: rich
Requires-Dist: fpdf
Requires-Dist: azure-identity
Requires-Dist: azure-mgmt-resource
